aiofutures/__init__.py
aiofutures/exceptions.py
aiofutures/executor.py
aiofutures/shortcuts.py
aiofutures-0.1.3.dist-info/LICENSE
aiofutures-0.1.3.dist-info/METADATA
aiofutures-0.1.3.dist-info/WHEEL
aiofutures-0.1.3.dist-info/RECORD
