Metadata-Version: 2.1
Name: aiofutures
Version: 0.1.3
Summary: Smoothly migrate your synchronous codebase to the asynchronous style.
Home-page: https://pypi.org/project/aiofutures
License: MIT
Keywords: asyncio,executor,concurrent,futures
Author: Denis Kazakov
Author-email: denis@kazakov.ru.net
Requires-Python: >=3.8.1
Classifier: Framework :: AsyncIO
Classifier: Intended Audience :: Developers
Classifier: License :: OSI Approved :: MIT License
Classifier: Programming Language :: Python :: 3
Classifier: Programming Language :: Python :: 3.9
Classifier: Programming Language :: Python :: 3.10
Classifier: Programming Language :: Python :: 3.11
Classifier: Programming Language :: Python :: 3.12
Classifier: Topic :: Software Development :: Libraries :: Python Modules
Classifier: Typing :: Typed
Project-URL: Repository, https://github.com/KazakovDenis/aiofutures
